py_photo_colorizer/__init__.py
py_photo_colorizer/__main__.py
py_photo_colorizer/colorizer.py
py_photo_colorizer-0.1.0.dist-info/WHEEL
py_photo_colorizer-0.1.0.dist-info/METADATA
py_photo_colorizer-0.1.0.dist-info/RECORD
