Metadata-Version: 2.1
Name: py-photo-colorizer
Version: 0.1.0
Summary: 
Author: RCJacH
Author-email: RCJacH@outlook.com
Requires-Python: >=3.10,<4.0
Classifier: Programming Language :: Python :: 3
Classifier: Programming Language :: Python :: 3.10
Requires-Dist: numpy (>=1.22.4,<2.0.0)
Requires-Dist: opencv-python (>=4.5.5,<5.0.0)
Requires-Dist: wget (>=3.2,<4.0)
